{
  "mppt_pv_voltage": 6.8,
  "mppt_pv_current": 0.0,
  "mppt_battery_soc": 90,
  "mppt_battery_voltage": 13.01,
  "mppt_battery_current": 0.0,
  "mppt_pv_power": 0.0,
  "mppt_battery_power": 0.0,
  "env_co2": 400.0,
  "env_temperature": 0.7,
  "env_humidity": 79.3,
  "ldr_lux": 0,
  "bms_cell_1_voltage": 3.273,
  "bms_cell_2_voltage": 3.284,
  "bms_cell_3_voltage": 3.282,
  "bms_cell_4_voltage": 3.279,
  "bms_battery_voltage": 13.11,
  "bms_battery_current": -2.6,
  "bms_battery_soc": 19,
  "bms_battery_soh": 0,
  "bms_battery_power": -34.09,
  "bms_discharge_mos_status": "ON",
  "bms_charge_mos_status": "ON",
  "timestamp": "2025-12-11T08:33:17.098628",
  "device_id": "KARADAG-BANK-01",
  "location": "Podgorica-Karadag",
  "device_type": 193
}